mystic_matchmaking/__init__.py
mystic_matchmaking/cli.py
mystic_matchmaking/mystic_matchmaking.py
mystic_matchmaking-0.1.0.dist-info/DESCRIPTION.rst
mystic_matchmaking-0.1.0.dist-info/METADATA
mystic_matchmaking-0.1.0.dist-info/RECORD
mystic_matchmaking-0.1.0.dist-info/WHEEL
mystic_matchmaking-0.1.0.dist-info/entry_points.txt
mystic_matchmaking-0.1.0.dist-info/metadata.json
mystic_matchmaking-0.1.0.dist-info/top_level.txt
