Metadata-Version: 2.0
Name: mystic-matchmaking
Version: 0.1.0
Summary: A simple matchmaking service you can visualize
Home-page: https://github.com/zhijiahu/mystic_matchmaking
Author: Hu Zhijia
Author-email: z.jia.hu@gmail.com
License: MIT license
Keywords: mystic_matchmaking
Platform: UNKNOWN
Classifier: Development Status :: 2 - Pre-Alpha
Classifier: Intended Audience :: Developers
Classifier: License :: OSI Approved :: MIT License
Classifier: Natural Language :: English
Classifier: Programming Language :: Python :: 2
Classifier: Programming Language :: Python :: 2.6
Classifier: Programming Language :: Python :: 2.7
Classifier: Programming Language :: Python :: 3
Classifier: Programming Language :: Python :: 3.3
Classifier: Programming Language :: Python :: 3.4
Classifier: Programming Language :: Python :: 3.5
Requires-Dist: Click (>=6.0)
